{"version":"0.0.1","type":"org.dcov.report.json.export","data":{"symbols":[{"column":42,"documented":true,"line":14,"name":"Asset","type":"Structure","file":"Model\/WebPImage.swift"},{"column":22,"documented":true,"line":21,"name":"Asset.defaultScale","type":"Variable","file":"Model\/WebPImage.swift"},{"column":33,"documented":true,"line":26,"name":"Asset.LoopMode","type":"Enumeration","file":"Model\/WebPImage.swift"},{"column":27,"documented":true,"line":29,"name":"Asset.LoopMode.infinite","type":"Case","file":"Model\/WebPImage.swift"},{"column":22,"documented":true,"line":32,"name":"Asset.LoopMode.once","type":"Case","file":"Model\/WebPImage.swift"},{"column":18,"documented":true,"line":35,"name":"Asset.LoopMode.`repeat`","type":"Case","file":"Model\/WebPImage.swift"},{"column":35,"documented":true,"line":38,"name":"Asset.LoopMode.amount","type":"Variable","file":"Model\/WebPImage.swift"},{"column":10,"documented":true,"line":47,"name":"Asset.LoopMode.init(amount:)","type":"Initializer","file":"Model\/WebPImage.swift"},{"column":6,"documented":true,"line":58,"name":"Asset.LoopMode.isAnimation","type":"Variable","file":"Model\/WebPImage.swift"},{"column":6,"documented":true,"line":63,"name":"Asset.LoopMode.frameCount","type":"Variable","file":"Model\/WebPImage.swift"},{"column":6,"documented":true,"line":68,"name":"Asset.LoopMode.duration","type":"Variable","file":"Model\/WebPImage.swift"},{"column":6,"documented":true,"line":73,"name":"Asset.LoopMode.frameDurations","type":"Variable","file":"Model\/WebPImage.swift"},{"column":6,"documented":true,"line":78,"name":"Asset.LoopMode.scale","type":"Variable","file":"Model\/WebPImage.swift"},{"column":30,"documented":true,"line":81,"name":"Asset.LoopMode.size","type":"Variable","file":"Model\/WebPImage.swift"},{"column":28,"documented":true,"line":84,"name":"Asset.LoopMode.canvasSize","type":"Variable","file":"Model\/WebPImage.swift"},{"column":34,"documented":true,"line":87,"name":"Asset.LoopMode.loopMode","type":"Variable","file":"Model\/WebPImage.swift"},{"column":34,"documented":true,"line":90,"name":"Asset.LoopMode.hasAlpha","type":"Variable","file":"Model\/WebPImage.swift"},{"column":6,"documented":true,"line":102,"name":"Asset.LoopMode.init(data:scale:)","type":"Initializer","file":"Model\/WebPImage.swift"},{"column":6,"documented":true,"line":119,"name":"Asset.LoopMode.init(url:)","type":"Initializer","file":"Model\/WebPImage.swift"},{"column":6,"documented":true,"line":138,"name":"Asset.LoopMode.init(named:bundle:)","type":"Initializer","file":"Model\/WebPImage.swift"},{"column":6,"documented":true,"line":147,"name":"Asset.LoopMode.cgImage(atFrame:)","type":"Function","file":"Model\/WebPImage.swift"},{"column":39,"documented":true,"line":6,"name":"ChronoImage","type":"Structure","file":"Model\/Image\/Image.swift"},{"column":28,"documented":true,"line":13,"name":"ChronoImage.defaultScale","type":"Variable","file":"Model\/Image\/Image.swift"},{"column":33,"documented":true,"line":18,"name":"ChronoImage.LoopMode","type":"Enumeration","file":"Model\/Image\/Image.swift"},{"column":27,"documented":true,"line":21,"name":"ChronoImage.LoopMode.infinite","type":"Case","file":"Model\/Image\/Image.swift"},{"column":22,"documented":true,"line":24,"name":"ChronoImage.LoopMode.once","type":"Case","file":"Model\/Image\/Image.swift"},{"column":18,"documented":true,"line":27,"name":"ChronoImage.LoopMode.`repeat`","type":"Case","file":"Model\/Image\/Image.swift"},{"column":35,"documented":true,"line":30,"name":"ChronoImage.LoopMode.amount","type":"Variable","file":"Model\/Image\/Image.swift"},{"column":10,"documented":true,"line":39,"name":"ChronoImage.LoopMode.init(amount:)","type":"Initializer","file":"Model\/Image\/Image.swift"},{"column":6,"documented":true,"line":50,"name":"ChronoImage.LoopMode.isAnimation","type":"Variable","file":"Model\/Image\/Image.swift"},{"column":6,"documented":true,"line":55,"name":"ChronoImage.LoopMode.frameCount","type":"Variable","file":"Model\/Image\/Image.swift"},{"column":6,"documented":true,"line":60,"name":"ChronoImage.LoopMode.duration","type":"Variable","file":"Model\/Image\/Image.swift"},{"column":6,"documented":true,"line":65,"name":"ChronoImage.LoopMode.frameDurations","type":"Variable","file":"Model\/Image\/Image.swift"},{"column":6,"documented":true,"line":70,"name":"ChronoImage.LoopMode.scale","type":"Variable","file":"Model\/Image\/Image.swift"},{"column":30,"documented":true,"line":73,"name":"ChronoImage.LoopMode.size","type":"Variable","file":"Model\/Image\/Image.swift"},{"column":28,"documented":true,"line":76,"name":"ChronoImage.LoopMode.canvasSize","type":"Variable","file":"Model\/Image\/Image.swift"},{"column":34,"documented":true,"line":79,"name":"ChronoImage.LoopMode.loopMode","type":"Variable","file":"Model\/Image\/Image.swift"},{"column":34,"documented":true,"line":82,"name":"ChronoImage.LoopMode.hasAlpha","type":"Variable","file":"Model\/Image\/Image.swift"},{"column":6,"documented":true,"line":94,"name":"ChronoImage.LoopMode.init(data:scale:)","type":"Initializer","file":"Model\/Image\/Image.swift"},{"column":6,"documented":true,"line":118,"name":"ChronoImage.LoopMode.init(url:)","type":"Initializer","file":"Model\/Image\/Image.swift"},{"column":6,"documented":true,"line":137,"name":"ChronoImage.LoopMode.init(named:bundle:)","type":"Initializer","file":"Model\/Image\/Image.swift"},{"column":6,"documented":true,"line":146,"name":"ChronoImage.LoopMode.cgImage(atFrame:)","type":"Function","file":"Model\/Image\/Image.swift"},{"column":52,"documented":true,"line":3,"name":"LoopImage.debugDescription","type":"Variable","file":"Model\/LoopImage+String.swift"},{"column":61,"documented":true,"line":25,"name":"LoopImage.LoopImage.LoopMode.debugDescription","type":"Variable","file":"Model\/LoopImage+String.swift"},{"column":56,"documented":true,"line":44,"name":"LoopImage.LoopImage.LoopMode.LoopImage.LoopMode.description","type":"Variable","file":"Model\/LoopImage+String.swift"},{"column":34,"documented":true,"line":7,"name":"LoopImage","type":"Structure","file":"Model\/LoopImage.swift"},{"column":6,"documented":true,"line":20,"name":"LoopImage.defaultScale","type":"Variable","file":"Model\/LoopImage.swift"},{"column":29,"documented":true,"line":25,"name":"LoopImage.LoopMode","type":"Enumeration","file":"Model\/LoopImage.swift"},{"column":27,"documented":true,"line":28,"name":"LoopImage.LoopMode.infinite","type":"Case","file":"Model\/LoopImage.swift"},{"column":22,"documented":true,"line":31,"name":"LoopImage.LoopMode.once","type":"Case","file":"Model\/LoopImage.swift"},{"column":18,"documented":true,"line":34,"name":"LoopImage.LoopMode.`repeat`","type":"Case","file":"Model\/LoopImage.swift"},{"column":35,"documented":true,"line":37,"name":"LoopImage.LoopMode.amount","type":"Variable","file":"Model\/LoopImage.swift"},{"column":10,"documented":true,"line":46,"name":"LoopImage.LoopMode.init(amount:)","type":"Initializer","file":"Model\/LoopImage.swift"},{"column":6,"documented":true,"line":57,"name":"LoopImage.LoopMode.isAnimation","type":"Variable","file":"Model\/LoopImage.swift"},{"column":6,"documented":true,"line":62,"name":"LoopImage.LoopMode.frameCount","type":"Variable","file":"Model\/LoopImage.swift"},{"column":6,"documented":true,"line":67,"name":"LoopImage.LoopMode.duration","type":"Variable","file":"Model\/LoopImage.swift"},{"column":6,"documented":true,"line":72,"name":"LoopImage.LoopMode.framesDuration","type":"Variable","file":"Model\/LoopImage.swift"},{"column":6,"documented":true,"line":77,"name":"LoopImage.LoopMode.scale","type":"Variable","file":"Model\/LoopImage.swift"},{"column":30,"documented":true,"line":80,"name":"LoopImage.LoopMode.size","type":"Variable","file":"Model\/LoopImage.swift"},{"column":28,"documented":true,"line":83,"name":"LoopImage.LoopMode.canvasSize","type":"Variable","file":"Model\/LoopImage.swift"},{"column":34,"documented":true,"line":86,"name":"LoopImage.LoopMode.loopMode","type":"Variable","file":"Model\/LoopImage.swift"},{"column":34,"documented":true,"line":89,"name":"LoopImage.LoopMode.hasAlpha","type":"Variable","file":"Model\/LoopImage.swift"},{"column":6,"documented":true,"line":101,"name":"LoopImage.LoopMode.init(data:scale:)","type":"Initializer","file":"Model\/LoopImage.swift"},{"column":6,"documented":true,"line":123,"name":"LoopImage.LoopMode.init(url:)","type":"Initializer","file":"Model\/LoopImage.swift"},{"column":6,"documented":true,"line":142,"name":"LoopImage.LoopMode.init(named:bundle:)","type":"Initializer","file":"Model\/LoopImage.swift"},{"column":6,"documented":true,"line":151,"name":"LoopImage.LoopMode.cgImage(atFrame:)","type":"Function","file":"Model\/LoopImage.swift"},{"column":48,"documented":true,"line":3,"name":"Frame.debugDescription","type":"Variable","file":"Model\/Frame+String.swift"},{"column":18,"documented":true,"line":1,"name":"LoopViewDelegate","type":"Protocol","file":"View\/UIKit\/LoopViewDelegate.swift"},{"column":42,"documented":true,"line":4,"name":"LoopViewDelegate.loopView(_:didStartPlayingImage:)","type":"Function","file":"View\/UIKit\/LoopViewDelegate.swift"},{"column":79,"documented":true,"line":10,"name":"LoopViewDelegate.loopView(_:didPausePlayingImage:)","type":"Function","file":"View\/UIKit\/LoopViewDelegate.swift"},{"column":79,"documented":true,"line":16,"name":"LoopViewDelegate.loopView(_:didStopPlayingImage:)","type":"Function","file":"View\/UIKit\/LoopViewDelegate.swift"},{"column":78,"documented":true,"line":22,"name":"LoopViewDelegate.loopView(_:didFinishPlayingImage:loopMode:)","type":"Function","file":"View\/UIKit\/LoopViewDelegate.swift"},{"column":20,"documented":true,"line":3,"name":"UIImage.init?(loopImage:atFrame:)","type":"Initializer","file":"View\/UIKit\/UIImage+LoopImage.swift"},{"column":22,"documented":true,"line":3,"name":"LoopImage.image(atFrame:)","type":"Function","file":"View\/UIKit\/LoopImage+UIImage.swift"},{"column":34,"documented":true,"line":3,"name":"LoopViewActivityDelegate","type":"Protocol","file":"View\/UIKit\/LoopViewActivityDelegate.swift"},{"column":50,"documented":true,"line":6,"name":"LoopViewActivityDelegate.loopView(_:didRenderFrameAtIndex:fromCache:)","type":"Function","file":"View\/UIKit\/LoopViewActivityDelegate.swift"},{"column":103,"documented":true,"line":13,"name":"LoopViewActivityDelegate.loopView(_:didDisplay:)","type":"Function","file":"View\/UIKit\/LoopViewActivityDelegate.swift"},{"column":22,"documented":true,"line":6,"name":"LoopImage.init(asset:bundle:)","type":"Initializer","file":"View\/UIKit\/LoopImage+NSDataAsset.swift"},{"column":13,"documented":true,"line":1,"name":"LoopView","type":"Class","file":"View\/UIKit\/LoopView.swift"},{"column":44,"documented":true,"line":4,"name":"LoopView.CompletionCallback","type":"Typealias","file":"View\/UIKit\/LoopView.swift"},{"column":48,"documented":true,"line":9,"name":"LoopView.delegate","type":"Variable","file":"View\/UIKit\/LoopView.swift"},{"column":46,"documented":true,"line":12,"name":"LoopView.activityDelegate","type":"Variable","file":"View\/UIKit\/LoopView.swift"},{"column":62,"documented":true,"line":15,"name":"LoopView.CompletionBehavior","type":"Enumeration","file":"View\/UIKit\/LoopView.swift"},{"column":37,"documented":true,"line":18,"name":"LoopView.CompletionBehavior.stop","type":"Case","file":"View\/UIKit\/LoopView.swift"},{"column":18,"documented":true,"line":21,"name":"LoopView.CompletionBehavior.pause","type":"Case","file":"View\/UIKit\/LoopView.swift"},{"column":6,"documented":true,"line":25,"name":"LoopView.CompletionBehavior.image","type":"Variable","file":"View\/UIKit\/LoopView.swift"},{"column":6,"documented":true,"line":39,"name":"LoopView.CompletionBehavior.displayScale","type":"Variable","file":"View\/UIKit\/LoopView.swift"},{"column":6,"documented":true,"line":48,"name":"LoopView.CompletionBehavior.contentMode","type":"Variable","file":"View\/UIKit\/LoopView.swift"},{"column":6,"documented":true,"line":55,"name":"LoopView.CompletionBehavior.autoPlay","type":"Variable","file":"View\/UIKit\/LoopView.swift"},{"column":6,"documented":true,"line":62,"name":"LoopView.CompletionBehavior.generateThumbnail","type":"Variable","file":"View\/UIKit\/LoopView.swift"},{"column":6,"documented":true,"line":70,"name":"LoopView.CompletionBehavior.interpolationQuality","type":"Variable","file":"View\/UIKit\/LoopView.swift"},{"column":6,"documented":true,"line":79,"name":"LoopView.CompletionBehavior.useCache","type":"Variable","file":"View\/UIKit\/LoopView.swift"},{"column":6,"documented":true,"line":88,"name":"LoopView.CompletionBehavior.playBackSpeedRate","type":"Variable","file":"View\/UIKit\/LoopView.swift"},{"column":6,"documented":true,"line":98,"name":"LoopView.CompletionBehavior.loopMode","type":"Variable","file":"View\/UIKit\/LoopView.swift"},{"column":6,"documented":true,"line":108,"name":"LoopView.CompletionBehavior.completionBehavior","type":"Variable","file":"View\/UIKit\/LoopView.swift"},{"column":60,"documented":true,"line":111,"name":"LoopView.CompletionBehavior.isPlaying","type":"Variable","file":"View\/UIKit\/LoopView.swift"},{"column":6,"documented":true,"line":120,"name":"LoopView.CompletionBehavior.layerClass","type":"Variable","file":"View\/UIKit\/LoopView.swift"},{"column":6,"documented":true,"line":125,"name":"LoopView.CompletionBehavior.intrinsicContentSize","type":"Variable","file":"View\/UIKit\/LoopView.swift"},{"column":6,"documented":true,"line":134,"name":"LoopView.CompletionBehavior.init(image:)","type":"Initializer","file":"View\/UIKit\/LoopView.swift"},{"column":6,"documented":true,"line":142,"name":"LoopView.CompletionBehavior.init(frame:)","type":"Initializer","file":"View\/UIKit\/LoopView.swift"},{"column":6,"documented":true,"line":149,"name":"LoopView.CompletionBehavior.init?(coder:)","type":"Initializer","file":"View\/UIKit\/LoopView.swift"},{"column":6,"documented":true,"line":161,"name":"LoopView.CompletionBehavior.play(loopMode:useCache:completion:)","type":"Function","file":"View\/UIKit\/LoopView.swift"},{"column":6,"documented":true,"line":182,"name":"LoopView.CompletionBehavior.playOnce(completion:)","type":"Function","file":"View\/UIKit\/LoopView.swift"},{"column":6,"documented":true,"line":188,"name":"LoopView.CompletionBehavior.playRepeat(amount:completion:)","type":"Function","file":"View\/UIKit\/LoopView.swift"},{"column":6,"documented":true,"line":195,"name":"LoopView.CompletionBehavior.playIndefinitely(completion:)","type":"Function","file":"View\/UIKit\/LoopView.swift"},{"column":6,"documented":true,"line":201,"name":"LoopView.CompletionBehavior.pause()","type":"Function","file":"View\/UIKit\/LoopView.swift"},{"column":6,"documented":true,"line":206,"name":"LoopView.CompletionBehavior.stop()","type":"Function","file":"View\/UIKit\/LoopView.swift"},{"column":6,"documented":true,"line":211,"name":"LoopView.CompletionBehavior.layoutSubviews()","type":"Function","file":"View\/UIKit\/LoopView.swift"},{"column":6,"documented":true,"line":223,"name":"LoopView.CompletionBehavior.didMoveToWindow()","type":"Function","file":"View\/UIKit\/LoopView.swift"},{"column":6,"documented":true,"line":229,"name":"LoopView.CompletionBehavior.didMoveToSuperview()","type":"Function","file":"View\/UIKit\/LoopView.swift"},{"column":15,"documented":true,"line":2,"name":"Loop","type":"Structure","file":"View\/SwiftUI\/Loop.swift"},{"column":46,"documented":true,"line":6,"name":"Loop.CompletionBehavior","type":"Enumeration","file":"View\/SwiftUI\/Loop.swift"},{"column":45,"documented":true,"line":9,"name":"Loop.CompletionBehavior.stop","type":"Case","file":"View\/SwiftUI\/Loop.swift"},{"column":18,"documented":true,"line":12,"name":"Loop.CompletionBehavior.pause","type":"Case","file":"View\/SwiftUI\/Loop.swift"},{"column":41,"documented":true,"line":82,"name":"Loop.CompletionBehavior.Renderer.Layout.Modifier.init(_:isPlaying:placeholder:)","type":"Initializer","file":"View\/SwiftUI\/Loop.swift"},{"column":6,"documented":true,"line":95,"name":"Loop.CompletionBehavior.Renderer.Layout.Modifier.init(_:isPlaying:placeholder:)","type":"Initializer","file":"View\/SwiftUI\/Loop.swift"},{"column":6,"documented":true,"line":106,"name":"Loop.CompletionBehavior.Renderer.Layout.Modifier.init(_:bundle:isPlaying:placeholder:)","type":"Initializer","file":"View\/SwiftUI\/Loop.swift"},{"column":6,"documented":true,"line":119,"name":"Loop.CompletionBehavior.Renderer.Layout.Modifier.body","type":"Variable","file":"View\/SwiftUI\/Loop.swift"},{"column":17,"documented":true,"line":165,"name":"Loop.CompletionBehavior.Renderer.Layout.Modifier.Loop.resizable(capInsets:resizingMode:)","type":"Function","file":"View\/SwiftUI\/Loop.swift"},{"column":6,"documented":true,"line":174,"name":"Loop.CompletionBehavior.Renderer.Layout.Modifier.Loop.renderingMode(_:)","type":"Function","file":"View\/SwiftUI\/Loop.swift"},{"column":6,"documented":true,"line":182,"name":"Loop.CompletionBehavior.Renderer.Layout.Modifier.Loop.interpolation(_:)","type":"Function","file":"View\/SwiftUI\/Loop.swift"},{"column":6,"documented":true,"line":190,"name":"Loop.CompletionBehavior.Renderer.Layout.Modifier.Loop.antialiased(_:)","type":"Function","file":"View\/SwiftUI\/Loop.swift"},{"column":17,"documented":true,"line":203,"name":"Loop.CompletionBehavior.Renderer.Layout.Modifier.Loop.Loop.completionBehavior(_:)","type":"Function","file":"View\/SwiftUI\/Loop.swift"},{"column":6,"documented":true,"line":212,"name":"Loop.CompletionBehavior.Renderer.Layout.Modifier.Loop.Loop.useCache(_:)","type":"Function","file":"View\/SwiftUI\/Loop.swift"},{"column":6,"documented":true,"line":221,"name":"Loop.CompletionBehavior.Renderer.Layout.Modifier.Loop.Loop.playBackSpeedRate(_:)","type":"Function","file":"View\/SwiftUI\/Loop.swift"},{"column":6,"documented":true,"line":231,"name":"Loop.CompletionBehavior.Renderer.Layout.Modifier.Loop.Loop.loopMode(_:)","type":"Function","file":"View\/SwiftUI\/Loop.swift"},{"column":6,"documented":true,"line":240,"name":"Loop.CompletionBehavior.Renderer.Layout.Modifier.Loop.Loop.onRender(_:)","type":"Function","file":"View\/SwiftUI\/Loop.swift"},{"column":6,"documented":true,"line":249,"name":"Loop.CompletionBehavior.Renderer.Layout.Modifier.Loop.Loop.onPlay(_:)","type":"Function","file":"View\/SwiftUI\/Loop.swift"},{"column":6,"documented":true,"line":258,"name":"Loop.CompletionBehavior.Renderer.Layout.Modifier.Loop.Loop.onPause(_:)","type":"Function","file":"View\/SwiftUI\/Loop.swift"},{"column":6,"documented":true,"line":267,"name":"Loop.CompletionBehavior.Renderer.Layout.Modifier.Loop.Loop.onStop(_:)","type":"Function","file":"View\/SwiftUI\/Loop.swift"},{"column":6,"documented":true,"line":276,"name":"Loop.CompletionBehavior.Renderer.Layout.Modifier.Loop.Loop.onRender(_:)","type":"Function","file":"View\/SwiftUI\/Loop.swift"},{"column":6,"documented":true,"line":285,"name":"Loop.CompletionBehavior.Renderer.Layout.Modifier.Loop.Loop.onComplete(_:)","type":"Function","file":"View\/SwiftUI\/Loop.swift"}],"files":{"Model\/LoopImage.swift":{"count":21,"documented":21,"percent":100},"View\/UIKit\/LoopImage+UIImage.swift":{"count":1,"documented":1,"percent":100},"Model\/LoopImage+String.swift":{"count":3,"documented":3,"percent":100},"View\/UIKit\/LoopViewActivityDelegate.swift":{"count":3,"documented":3,"percent":100},"View\/SwiftUI\/Loop.swift":{"count":22,"documented":22,"percent":100},"View\/UIKit\/LoopView.swift":{"count":32,"documented":32,"percent":100},"View\/UIKit\/LoopImage+NSDataAsset.swift":{"count":1,"documented":1,"percent":100},"View\/UIKit\/UIImage+LoopImage.swift":{"count":1,"documented":1,"percent":100},"Model\/WebPImage.swift":{"count":21,"documented":21,"percent":100},"View\/UIKit\/LoopViewDelegate.swift":{"count":5,"documented":5,"percent":100},"Model\/Image\/Image.swift":{"count":21,"documented":21,"percent":100},"Model\/Frame+String.swift":{"count":1,"documented":1,"percent":100}},"totals":{"count":132,"documented":132,"percent":100}}}